lappy
